q2/__init__.py
q2/abundances.py
q2/config.py
q2/errors.py
q2/isopars.py
q2/modatm.py
q2/moog.py
q2/specpars.py
q2/star.py
q2/tools.py
qoyllur_quipu-1.0.2.dist-info/METADATA
qoyllur_quipu-1.0.2.dist-info/WHEEL
qoyllur_quipu-1.0.2.dist-info/top_level.txt
qoyllur_quipu-1.0.2.dist-info/RECORD
