Metadata-Version: 2.1
Name: qoyllur-quipu
Version: 1.0.2
Summary: q2 Python Package
Home-page: https://github.com/astroChasqui/q2
Author: Ivan Ramirez
Author-email: iramirez@tacomacc.edu
License: BSD 2-Clause 'Simplified' License
Classifier: Programming Language :: Python :: 3
Classifier: Operating System :: OS Independent
Requires-Python: >=3.5
Requires-Dist: numpy
Requires-Dist: scipy
Requires-Dist: matplotlib
